Metadata-Version: 2.4
Name: bce-python-sdk-next
Version: 203.0.9.42
Summary: BCE SDK for python
Home-page: http://bce.baidu.com
Author: atorber
Author-email: atorber@163.com
License: Apache License 2.0
Requires-Python: >=2.7, !=3.0.*, !=3.1.*, !=3.2.*, <4
License-File: LICENSE
Requires-Dist: pycryptodome>=3.8.0
Requires-Dist: future>=0.6.0
Requires-Dist: six>=1.4.0
Dynamic: author
Dynamic: author-email
Dynamic: description
Dynamic: home-page
Dynamic: license
Dynamic: license-file
Dynamic: requires-dist
Dynamic: requires-python
Dynamic: summary
